[
    {"date": "August26", "session": "00", "day": ""},

    {"date": "August28", "session": "01", "day": "B"},
    {"date": "September03", "session": "02", "day": "B"},

    {"date": "September05", "session": "03", "day": "B"},

    {"date": "September09", "session": "04", "day": "B"},

    {"date": "September11", "session": "05", "day": "B"},

    {"date": "September13", "session": "06", "day": "B"},

    {"date": "September17", "session": "07", "day": "B"},

    {"date": "September19", "session": "SUB", "day": "B"},

    {"date": "September23", "session": "08", "day": "B"},

    {"date": "September25", "session": "09", "day": "B"},

    {"date": "September27", "session": "10", "day": "B"},

    {"date": "October01", "session": "11", "day": "B"},

    {"date": "October04", "session": "12", "day": "B"},

    {"date": "October08", "session": "13", "day": "B"},
    {"date": "October15", "session": "14", "day": "B"},

    {"date": "October17", "session": "15", "day": "B"},

    {"date": "October21", "session": "16", "day": "B"},

    {"date": "October23", "session": "17", "day": "B"},

    {"date": "October25", "session": "18", "day": "B"},

    {"date": "October29", "session": "19", "day": "B"},

    {"date": "October31", "session": "20", "day": "B"},

    {"date": "November07", "session": "21", "day": "B"},

    {"date": "November12", "session": "22", "day": "B"},

    {"date": "November14", "session": "23", "day": "B"},

    {"date": "November18", "session": "24", "day": "B"},

    {"date": "November20", "session": "25", "day": "B"},

    {"date": "November22", "session": "26", "day": "B"},

    {"date": "November26", "session": "27", "day": "B"},

    {"date": "December03", "session": "28", "day": "B"},

    {"date": "December05", "session": "29", "day": "B"},

    {"date": "December09", "session": "30", "day": "B"},

    {"date": "December11", "session": "31", "day": "B"},

    {"date": "December13", "session": "32", "day": "B"},

    {"date": "December17", "session": "33", "day": "B"},

    {"date": "December19", "session": "34", "day": "B"},
    {"date": "January06", "session": "35", "day": "B"},

    {"date": "January08", "session": "36", "day": "B"},

    {"date": "January10", "session": "37", "day": "B"},

    {"date": "January14", "session": "38", "day": "B"},

    {"date": "January16", "session": "39", "day": "B"},

    {"date": "January21", "session": "40", "day": "B"},

    {"date": "January23", "session": "TBD", "day": "B"},

    {"date": "January27", "session": "TBD", "day": "B"},

    {"date": "January29", "session": "TBD", "day": "B"}
    ]